odoo/addons/__init__.py
odoo/addons/crm_project/__init__.py
odoo/addons/crm_project/__manifest__.py
odoo/addons/crm_project/i18n/af.po
odoo/addons/crm_project/i18n/am.po
odoo/addons/crm_project/i18n/ar.po
odoo/addons/crm_project/i18n/bg.po
odoo/addons/crm_project/i18n/bs.po
odoo/addons/crm_project/i18n/ca.po
odoo/addons/crm_project/i18n/cs.po
odoo/addons/crm_project/i18n/da.po
odoo/addons/crm_project/i18n/de.po
odoo/addons/crm_project/i18n/el.po
odoo/addons/crm_project/i18n/en_AU.po
odoo/addons/crm_project/i18n/en_GB.po
odoo/addons/crm_project/i18n/es.po
odoo/addons/crm_project/i18n/es_BO.po
odoo/addons/crm_project/i18n/es_CL.po
odoo/addons/crm_project/i18n/es_CO.po
odoo/addons/crm_project/i18n/es_CR.po
odoo/addons/crm_project/i18n/es_DO.po
odoo/addons/crm_project/i18n/es_EC.po
odoo/addons/crm_project/i18n/es_PA.po
odoo/addons/crm_project/i18n/es_PE.po
odoo/addons/crm_project/i18n/es_PY.po
odoo/addons/crm_project/i18n/es_VE.po
odoo/addons/crm_project/i18n/et.po
odoo/addons/crm_project/i18n/eu.po
odoo/addons/crm_project/i18n/fa.po
odoo/addons/crm_project/i18n/fi.po
odoo/addons/crm_project/i18n/fo.po
odoo/addons/crm_project/i18n/fr.po
odoo/addons/crm_project/i18n/fr_BE.po
odoo/addons/crm_project/i18n/fr_CA.po
odoo/addons/crm_project/i18n/gl.po
odoo/addons/crm_project/i18n/gu.po
odoo/addons/crm_project/i18n/he.po
odoo/addons/crm_project/i18n/hi.po
odoo/addons/crm_project/i18n/hr.po
odoo/addons/crm_project/i18n/hu.po
odoo/addons/crm_project/i18n/hy.po
odoo/addons/crm_project/i18n/id.po
odoo/addons/crm_project/i18n/is.po
odoo/addons/crm_project/i18n/it.po
odoo/addons/crm_project/i18n/ja.po
odoo/addons/crm_project/i18n/ka.po
odoo/addons/crm_project/i18n/kab.po
odoo/addons/crm_project/i18n/kk.po
odoo/addons/crm_project/i18n/ko.po
odoo/addons/crm_project/i18n/ln.po
odoo/addons/crm_project/i18n/lo.po
odoo/addons/crm_project/i18n/lt.po
odoo/addons/crm_project/i18n/lv.po
odoo/addons/crm_project/i18n/mk.po
odoo/addons/crm_project/i18n/ml_IN.po
odooku_odoo_project-11.0.7.dist-info/LICENSE
odooku_odoo_project-11.0.7.dist-info/METADATA
odooku_odoo_project-11.0.7.dist-info/WHEEL
odooku_odoo_project-11.0.7.dist-info/top_level.txt
odooku_odoo_project-11.0.7.dist-info/RECORD
